[{"ticker":"ZIFI11","preco":900,"nome":"FII ZION    CI","data_atualizacao":"26/01/2026 20:26"},{"ticker":"ZAVI11","preco":10.3,"nome":"FII ZAVIT R CI","data_atualizacao":"26/01/2026 20:26"},{"ticker":"ZAVC11","preco":9.13,"nome":"FII ZAVIT C CI","data_atualizacao":"26/01/2026 20:26"},{"ticker":"ZAGH11","preco":9.99,"nome":"FII ZAGH    CI  ER","data_atualizacao":"26/01/2026 20:26"},{"ticker":"YUFI11","preco":15,"nome":"FII YUCA    CI","data_atualizacao":"26/01/2026 20:26"},{"ticker":"YEES11","preco":102,"nome":"FII YEES    CI","data_atualizacao":"26/01/2026 20:26"},{"ticker":"YCHY11","preco":1000,"nome":"YCHY11.SA,0P0001K6XM,0","data_atualizacao":"26/01/2026 20:26"},{"ticker":"XPSF11","preco":6.67,"nome":"FII XP SELECCI","data_atualizacao":"26/01/2026 20:26"},{"ticker":"XPIN11","preco":79.99,"nome":"FII XP INDL CI  ER","data_atualizacao":"26/01/2026 20:26"},{"ticker":"XPID11","preco":51.5,"nome":"FIRF XP IE  CI","data_atualizacao":"26/01/2026 20:26"},{"ticker":"XPHT11","preco":123,"nome":"XPHT11.SA,0P0001K6XJ,0","data_atualizacao":"26/01/2026 20:26"},{"ticker":"XPCM11","preco":8,"nome":"FII XP MACAECI","data_atualizacao":"26/01/2026 20:26"},{"ticker":"XPCI11","preco":85.93,"nome":"FII XP CRED CI","data_atualizacao":"26/01/2026 20:26"},{"ticker":"XPCA11","preco":8.45,"nome":"FIAGRO XP CACI","data_atualizacao":"26/01/2026 20:26"},{"ticker":"WSEC11","preco":1.41,"nome":"FII WARREN  CI","data_atualizacao":"26/01/2026 20:26"},{"ticker":"WPLZ11","preco":50.72,"nome":"FII W PLAZA CI","data_atualizacao":"26/01/2026 20:26"},{"ticker":"WHGR11","preco":9.7,"nome":"FII WHG REALCI","data_atualizacao":"26/01/2026 20:26"},{"ticker":"VXXV11","preco":725,"nome":"FII VX XVI  CI","data_atualizacao":"26/01/2026 20:26"},{"ticker":"VVRI11","preco":89.99,"nome":"FII V2 RENDACI  ER","data_atualizacao":"26/01/2026 20:26"},{"ticker":"VVPR11","preco":101.5,"nome":"VVPR11.SA,0P0001K6XH,0","data_atualizacao":"26/01/2026 20:26"},{"ticker":"VVMR11","preco":84.98,"nome":"FII MULT RENCI","data_atualizacao":"26/01/2026 20:26"},{"ticker":"VVCR11","preco":9.55,"nome":"FII V2 RECE CI  ER","data_atualizacao":"26/01/2026 20:26"},{"ticker":"VVCO11","preco":14.99,"nome":"FII V2EDCORPCI","data_atualizacao":"26/01/2026 20:26"},{"ticker":"VTPL11","preco":65.9,"nome":"FII PLUS    CI","data_atualizacao":"26/01/2026 20:26"},{"ticker":"VTLT11","preco":88.98,"nome":"FII VOT LOG CI","data_atualizacao":"26/01/2026 20:26"},{"ticker":"VSLH11","preco":2.21,"nome":"FII VERS CRICI","data_atualizacao":"26/01/2026 20:26"},{"ticker":"VSHO11","preco":75.55,"nome":"FII VOT SHOPCI","data_atualizacao":"26/01/2026 20:26"},{"ticker":"VRTM11","preco":7.31,"nome":"FII VRTM    CI","data_atualizacao":"26/01/2026 20:26"},{"ticker":"VRTA11","preco":79.82,"nome":"FII FATOR VECI","data_atualizacao":"26/01/2026 20:26"},{"ticker":"VPSI11","preco":22.38,"nome":"FII POLO SHOCI  ER","data_atualizacao":"26/01/2026 20:26"},{"ticker":"VPPR11","preco":17.51,"nome":"FII V2 PRIMECI","data_atualizacao":"26/01/2026 20:26"},{"ticker":"VOTS11","preco":80.1,"nome":"FII V MASTERCI","data_atualizacao":"26/01/2026 20:26"},{"ticker":"VJFD11","preco":148.01,"nome":"FII JFDCAM  CI","data_atualizacao":"26/01/2026 20:26"},{"ticker":"VIUR11","preco":5.99,"nome":"FII VINCI IUCI","data_atualizacao":"26/01/2026 20:26"},{"ticker":"VINO11","preco":5.43,"nome":"FII VINCI OFCI","data_atualizacao":"26/01/2026 20:26"},{"ticker":"VILG11","preco":102.4,"nome":"FII VINCI LGCI","data_atualizacao":"26/01/2026 20:26"},{"ticker":"VIFI11","preco":7.46,"nome":"FII VINCI IFCI","data_atualizacao":"26/01/2026 20:26"},{"ticker":"VGRI11","preco":8.66,"nome":"FII VGRI    CI","data_atualizacao":"26/01/2026 20:26"},{"ticker":"VGIR11","preco":9.85,"nome":"FII VALREIIICI  ER","data_atualizacao":"26/01/2026 20:26"},{"ticker":"VGIP11","preco":84.98,"nome":"FII VALORAIPCI  ER","data_atualizacao":"26/01/2026 20:26"},{"ticker":"VGII11","preco":72.84,"nome":"FII VGII    CI","data_atualizacao":"26/01/2026 20:26"},{"ticker":"VGIA11","preco":9.99,"nome":"FIAGRO VGIA CI  ER","data_atualizacao":"26/01/2026 20:26"},{"ticker":"VERE11","preco":445.76,"nome":"VERE11.SA,0P00013U3H,0","data_atualizacao":"26/01/2026 20:26"},{"ticker":"VCRR11","preco":68.2,"nome":"FII VECT RENCI","data_atualizacao":"26/01/2026 20:26"},{"ticker":"VCRI11","preco":7.62,"nome":"FII VINCI CRCI","data_atualizacao":"26/01/2026 20:26"},{"ticker":"VCRA11","preco":66.99,"nome":"FIAGRO VCRA CI","data_atualizacao":"26/01/2026 20:26"},{"ticker":"VCJR11","preco":80.56,"nome":"FII VECTIS  CI","data_atualizacao":"26/01/2026 20:26"},{"ticker":"VANG11","preco":101.57,"nome":"VANG INFRA  CI","data_atualizacao":"26/01/2026 20:26"},{"ticker":"URPR11","preco":43.39,"nome":"FII URCA RENCI","data_atualizacao":"26/01/2026 20:26"},{"ticker":"URHF11","preco":73,"nome":"FII URHF    CI","data_atualizacao":"26/01/2026 20:26"},{"ticker":"SHPH11","preco":947.45,"nome":"FII HIGIENOPCI","data_atualizacao":"26/01/2026 20:26"},{"ticker":"SHOP11","preco":55,"nome":"FII MULTSHOPCI  ES","data_atualizacao":"26/01/2026 20:26"},{"ticker":"SEQR11","preco":53.32,"nome":"FII SEQUOIA CI","data_atualizacao":"26/01/2026 20:26"},{"ticker":"SEED11","preco":100,"nome":"FII HEDGE SDCI","data_atualizacao":"26/01/2026 20:26"},{"ticker":"SDIL11","preco":96.5,"nome":"SDIL11.SA,0P00013U4J,0","data_atualizacao":"26/01/2026 20:26"},{"ticker":"SCPF11","preco":2.74,"nome":"FII SCP     CI","data_atualizacao":"26/01/2026 20:26"},{"ticker":"SARE11","preco":4.75,"nome":"FII SANT RENCI","data_atualizacao":"26/01/2026 20:26"},{"ticker":"SAPI11","preco":9.17,"nome":"FII SAPI    CI","data_atualizacao":"26/01/2026 20:26"},{"ticker":"SADI11","preco":0,"nome":"FII SANT PAPCI","data_atualizacao":"26/01/2026 20:26"},{"ticker":"SAAG11","preco":106.61,"nome":"SAAG11.SA,0P00013U4H,0","data_atualizacao":"26/01/2026 20:26"},{"ticker":"RZZR11","preco":137.4,"nome":"FII RZZR    CI  ER","data_atualizacao":"26/01/2026 20:26"},{"ticker":"RZZI11","preco":1000,"nome":"FII RZZI    CI","data_atualizacao":"26/01/2026 20:26"},{"ticker":"RZTR11","preco":97.7,"nome":"FII RIZA TX CI","data_atualizacao":"26/01/2026 20:26"},{"ticker":"RZLC11","preco":1009.64,"nome":"FII RZLC    CI","data_atualizacao":"26/01/2026 20:26"},{"ticker":"RZEO11","preco":190,"nome":"FIAGRO RZEO CI","data_atualizacao":"26/01/2026 20:26"},{"ticker":"RZAT11","preco":90.64,"nome":"FII ARCTIUM CI  ER","data_atualizacao":"26/01/2026 20:26"},{"ticker":"RZAK11","preco":85.57,"nome":"FII RIZA AKNCI  ER","data_atualizacao":"26/01/2026 20:26"},{"ticker":"RZAG11","preco":9.46,"nome":"FIAGRO RIZA CI","data_atualizacao":"26/01/2026 20:26"},{"ticker":"RVBI11","preco":59.9,"nome":"FII RVBI VBICI","data_atualizacao":"26/01/2026 20:26"},{"ticker":"RURA11","preco":8.82,"nome":"FIAGRO RURA CI","data_atualizacao":"26/01/2026 20:26"},{"ticker":"RSPD11","preco":850,"nome":"FII RBRESID3CI","data_atualizacao":"26/01/2026 20:26"},{"ticker":"RRCI11","preco":80.25,"nome":"FII RBCAP RICI","data_atualizacao":"26/01/2026 20:26"},{"ticker":"RPRI11","preco":88.24,"nome":"FII RBR PR  CI","data_atualizacao":"26/01/2026 20:26"},{"ticker":"ROOF11","preco":350,"nome":"FII ROOFTOPICI","data_atualizacao":"26/01/2026 20:26"},{"ticker":"RNGO11","preco":52.24,"nome":"FII RIONEGROCI","data_atualizacao":"26/01/2026 20:26"},{"ticker":"RNDP11","preco":0,"nome":"FII BB R PAPCI","data_atualizacao":"26/01/2026 20:26"},{"ticker":"RMAI11","preco":39.99,"nome":"FII REAGMULTCI  ER","data_atualizacao":"26/01/2026 20:26"},{"ticker":"RINV11","preco":110,"nome":"FII REAL INVCI  ER","data_atualizacao":"26/01/2026 20:26"},{"ticker":"RIFF11","preco":8.09,"nome":"FI INFRA RIFCI","data_atualizacao":"26/01/2026 20:26"},{"ticker":"RFOF11","preco":64.49,"nome":"FII RB CFOF CI","data_atualizacao":"26/01/2026 20:26"},{"ticker":"RENV11","preco":7.16,"nome":"FII RENV    CI","data_atualizacao":"26/01/2026 20:26"},{"ticker":"RELG11","preco":64.15,"nome":"FII REC LOG CI","data_atualizacao":"26/01/2026 20:26"},{"ticker":"REIT11","preco":104.5,"nome":"FII REIT RIVCI  EA","data_atualizacao":"26/01/2026 20:26"},{"ticker":"RECX11","preco":67.99,"nome":"FII REC FOF CI","data_atualizacao":"26/01/2026 20:26"},{"ticker":"RECR11","preco":82.72,"nome":"FII REC RECECI","data_atualizacao":"26/01/2026 20:26"},{"ticker":"RECM11","preco":8.69,"nome":"FII RECM    CI","data_atualizacao":"26/01/2026 20:26"},{"ticker":"RECD11","preco":7.76,"nome":"FII RECD    CI","data_atualizacao":"26/01/2026 20:26"},{"ticker":"RDLI11","preco":99.98,"nome":"FII RDLI    CI  ER","data_atualizacao":"26/01/2026 20:26"},{"ticker":"RDES11","preco":58,"nome":"RDES11.SA,0P00013U4D,0","data_atualizacao":"26/01/2026 20:26"},{"ticker":"RCRI11B","preco":1200,"nome":"RCRI11B.SA,0P0001IFQ9,0","data_atualizacao":"26/01/2026 20:26"},{"ticker":"RCRB11","preco":142.33,"nome":"FII RIOB RC CI","data_atualizacao":"26/01/2026 20:26"},{"ticker":"RCFF11","preco":90,"nome":"FII RBR FEEDCI  ER","data_atualizacao":"26/01/2026 20:26"},{"ticker":"RCFA11","preco":0.92,"nome":"FII GP RCFA CI","data_atualizacao":"26/01/2026 20:26"},{"ticker":"RBVA11","preco":9.99,"nome":"FII RIOB VA CI","data_atualizacao":"26/01/2026 20:26"},{"ticker":"RBTS11","preco":302.02,"nome":"FII RB TFO  CI","data_atualizacao":"26/01/2026 20:26"},{"ticker":"RBRY11","preco":98.15,"nome":"FII RBR PCRICI","data_atualizacao":"26/01/2026 20:26"},{"ticker":"RBRX11","preco":8.4,"nome":"FII RBR MULTCI  ER","data_atualizacao":"26/01/2026 20:26"},{"ticker":"RBRS11","preco":34.56,"nome":"FII RIOB RR CI","data_atualizacao":"26/01/2026 20:26"},{"ticker":"RBRM11","preco":160000,"nome":"RBRM11.SA,0P0001K6X5,0","data_atualizacao":"26/01/2026 20:26"},{"ticker":"RBRL11","preco":92.92,"nome":"FII RBR LOG CI","data_atualizacao":"26/01/2026 20:26"},{"ticker":"RBRI11","preco":624,"nome":"FII RBR III CI","data_atualizacao":"26/01/2026 20:26"},{"ticker":"RBRF11","preco":6.65,"nome":"FII RBRALPHACI","data_atualizacao":"26/01/2026 20:26"},{"ticker":"RBRD11","preco":41.5,"nome":"FII RB II   CI","data_atualizacao":"26/01/2026 20:26"},{"ticker":"RBOP11","preco":212.01,"nome":"FII MERC BR CI","data_atualizacao":"26/01/2026 20:26"},{"ticker":"RBLG11","preco":60,"nome":"FII RBCAP LGCI","data_atualizacao":"26/01/2026 20:26"},{"ticker":"RBIR11","preco":93.19,"nome":"FII RBRES IVCI","data_atualizacao":"26/01/2026 20:26"},{"ticker":"RBIF11","preco":77.57,"nome":"FIC FI RB ESCI","data_atualizacao":"26/01/2026 20:26"},{"ticker":"RBHY11","preco":79.69,"nome":"FII RB YIELDCI","data_atualizacao":"26/01/2026 20:26"},{"ticker":"RBHG11","preco":67.75,"nome":"FII RBCRI IVCI","data_atualizacao":"26/01/2026 20:26"},{"ticker":"RBGS11","preco":28.45,"nome":"RBGS11.SA,0P00013U47,0","data_atualizacao":"26/01/2026 20:26"},{"ticker":"RBFF11","preco":10.65,"nome":"FII RIOB FF CI","data_atualizacao":"26/01/2026 20:26"},{"ticker":"RBED11","preco":94.03,"nome":"FII RIOB ED CI  ER","data_atualizacao":"26/01/2026 20:26"},{"ticker":"RBDS11","preco":2.9,"nome":"FII RBRESID2CI","data_atualizacao":"26/01/2026 20:26"},{"ticker":"RBCO11","preco":44,"nome":"RBCO11.SA,0P0001K61A,0","data_atualizacao":"26/01/2026 20:26"},{"ticker":"RBCB11","preco":19,"nome":"RBCB11.SA,0P00013U4F,0","data_atualizacao":"26/01/2026 20:26"},{"ticker":"RBBV11","preco":100,"nome":"RBBV11.SA,0P00013U3O,0","data_atualizacao":"26/01/2026 20:26"},{"ticker":"QAMI11","preco":0,"nome":"FII QUASAR CCI","data_atualizacao":"26/01/2026 20:26"},{"ticker":"PURB11","preco":95.1,"nome":"PURB11.SA,0P0001OI0U,0","data_atualizacao":"26/01/2026 20:26"},{"ticker":"PULV11","preco":8.82,"nome":"FII PULV    CI","data_atualizacao":"26/01/2026 20:26"},{"ticker":"PRSV11","preco":34.45,"nome":"FII P VARGASCI","data_atualizacao":"26/01/2026 20:26"},{"ticker":"PQDP11","preco":2300,"nome":"FII D PEDRO CI","data_atualizacao":"26/01/2026 20:26"},{"ticker":"PQAG11","preco":54.77,"nome":"FII PARQ ANHCI","data_atualizacao":"26/01/2026 20:26"},{"ticker":"PORD11","preco":8.3,"nome":"FII POLO CRICI","data_atualizacao":"26/01/2026 20:26"},{"ticker":"PNRC11","preco":61,"nome":"FII PNRC    CI  EA","data_atualizacao":"26/01/2026 20:26"},{"ticker":"PNPR11","preco":48,"nome":"FII PAN PROPCI","data_atualizacao":"26/01/2026 20:26"},{"ticker":"MORE11","preco":0,"nome":"FII MORE RE CI","data_atualizacao":"26/01/2026 20:26"},{"ticker":"MORC11","preco":0,"nome":"FII MORE CRICI","data_atualizacao":"26/01/2026 20:26"},{"ticker":"MMVE11","preco":147,"nome":"FII MMVE OP CI","data_atualizacao":"26/01/2026 20:26"},{"ticker":"MMPD11","preco":110.61,"nome":"MMPD11.SA,0P0001R8JN,0","data_atualizacao":"26/01/2026 20:26"},{"ticker":"MGIM11","preco":101.5,"nome":"MGIM11.SA,0P0001OH5V,0","data_atualizacao":"26/01/2026 20:26"},{"ticker":"MGHT11","preco":16.9,"nome":"FII MOGNO HTCI","data_atualizacao":"26/01/2026 20:26"},{"ticker":"MGCR11","preco":9.4,"nome":"MGCR11.SA,0P0001OI10,0","data_atualizacao":"26/01/2026 20:26"},{"ticker":"MFII11","preco":80.44,"nome":"FII MERITO ICI","data_atualizacao":"26/01/2026 20:26"},{"ticker":"MFCR11","preco":24.6,"nome":"FII MERITO RCI","data_atualizacao":"26/01/2026 20:26"},{"ticker":"MCEM11","preco":66.26,"nome":"FII MCEM    CI","data_atualizacao":"26/01/2026 20:26"},{"ticker":"MCCI11","preco":92.41,"nome":"FII MAUA    CI  ER","data_atualizacao":"26/01/2026 20:26"},{"ticker":"MBRF11","preco":369.4,"nome":"MBRF11.SA,0P00013U37,48","data_atualizacao":"26/01/2026 20:26"},{"ticker":"MAXR11","preco":63,"nome":"FII MAX RET CI","data_atualizacao":"26/01/2026 20:26"},{"ticker":"MATV11","preco":86.63,"nome":"FII MORE ATVCI","data_atualizacao":"26/01/2026 20:26"},{"ticker":"MANA11","preco":9.32,"nome":"FII MANATI  CI","data_atualizacao":"26/01/2026 20:26"},{"ticker":"LVBI11","preco":111,"nome":"FII LVBI VBICI","data_atualizacao":"26/01/2026 20:26"},{"ticker":"LTMT11","preco":98.36,"nome":"FII SPECIALECI","data_atualizacao":"26/01/2026 20:26"},{"ticker":"LSPA11","preco":24.01,"nome":"FII LESTE PACI","data_atualizacao":"26/01/2026 20:26"},{"ticker":"LSOI11","preco":12.26,"nome":"FII LSOI    CI","data_atualizacao":"26/01/2026 20:26"},{"ticker":"LSAG11","preco":90,"nome":"FIAGRO LESTECI","data_atualizacao":"26/01/2026 20:26"},{"ticker":"LRED11","preco":12.35,"nome":"FII LRED    CI","data_atualizacao":"26/01/2026 20:26"},{"ticker":"LRDI11","preco":198,"nome":"FII LEBLON  CI  ER","data_atualizacao":"26/01/2026 20:26"},{"ticker":"LPLP11","preco":300,"nome":"FII LAGO PDRCI","data_atualizacao":"26/01/2026 20:26"},{"ticker":"LOFT11B","preco":29.9,"nome":"LOFT11B.SA,0P0001K5X0,0","data_atualizacao":"26/01/2026 20:26"},{"ticker":"LLAO11","preco":57.2,"nome":"FII BS2     CI","data_atualizacao":"26/01/2026 20:26"},{"ticker":"LKDV11","preco":1081.93,"nome":"FII DEV ONE CI","data_atualizacao":"26/01/2026 20:26"},{"ticker":"LIFE11","preco":8.78,"nome":"FII LIFE    CI","data_atualizacao":"26/01/2026 20:26"},{"ticker":"LFTT11","preco":0,"nome":"FII LOFT II CI","data_atualizacao":"26/01/2026 20:26"},{"ticker":"LASC11","preco":110.24,"nome":"FII LEGATUS CI","data_atualizacao":"26/01/2026 20:26"},{"ticker":"LAFI11","preco":116.51,"nome":"FIAGRO LAFI CI","data_atualizacao":"26/01/2026 20:26"},{"ticker":"KORE11","preco":76.88,"nome":"FII KORE    CI","data_atualizacao":"26/01/2026 20:26"},{"ticker":"PNDL11","preco":1200,"nome":"FII PANORAMACI","data_atualizacao":"26/01/2026 20:26"},{"ticker":"PNCR11","preco":0,"nome":"FII PNCR    CI  ER","data_atualizacao":"26/01/2026 20:26"},{"ticker":"PMLL11","preco":104.82,"nome":"FII PMLL PAXCI","data_atualizacao":"26/01/2026 20:26"},{"ticker":"PMIS11","preco":8.46,"nome":"FII PMIS    CI","data_atualizacao":"26/01/2026 20:26"},{"ticker":"PMFO11","preco":91.09,"nome":"FII PMFO    CI","data_atualizacao":"26/01/2026 20:26"},{"ticker":"PLRI11","preco":9.1,"nome":"FII POLO I  CI","data_atualizacao":"26/01/2026 20:26"},{"ticker":"PLCR11","preco":79.1,"nome":"FII PLURAL RCI","data_atualizacao":"26/01/2026 20:26"},{"ticker":"PLCA11","preco":81.5,"nome":"FIAGRO PLUR CI","data_atualizacao":"26/01/2026 20:26"},{"ticker":"PLAG11","preco":52.99,"nome":"FII PLAG    CI","data_atualizacao":"26/01/2026 20:26"},{"ticker":"PEMA11","preco":41.25,"nome":"FII PERFORMACI","data_atualizacao":"26/01/2026 20:26"},{"ticker":"PATL11","preco":67.19,"nome":"FII PATL VBICI","data_atualizacao":"26/01/2026 20:26"},{"ticker":"PATC11","preco":41.02,"nome":"FII PATC VBICI","data_atualizacao":"26/01/2026 20:26"},{"ticker":"PATA11","preco":10.37,"nome":"FII PATA    CI","data_atualizacao":"26/01/2026 20:26"},{"ticker":"PABY11","preco":13.76,"nome":"FII PANAMBY CI","data_atualizacao":"26/01/2026 20:26"},{"ticker":"OURE11","preco":78.2,"nome":"FII OU RENDACI","data_atualizacao":"26/01/2026 20:26"},{"ticker":"OULG11","preco":24.04,"nome":"FII OURILOG CI","data_atualizacao":"26/01/2026 20:26"},{"ticker":"OUJP11","preco":83.6,"nome":"FII OURI JPPCI","data_atualizacao":"26/01/2026 20:26"},{"ticker":"OUFF11","preco":61.1,"nome":"FII OURI FOFCI","data_atualizacao":"26/01/2026 20:26"},{"ticker":"ONEF11","preco":200.03,"nome":"ONEF11.SA,0P00013U3F,0","data_atualizacao":"26/01/2026 20:26"},{"ticker":"ONDV11","preco":9.77,"nome":"FII ONDV    CI","data_atualizacao":"26/01/2026 20:26"},{"ticker":"OIAG11","preco":8.89,"nome":"FIAGRO INNOVCI","data_atualizacao":"26/01/2026 20:26"},{"ticker":"OGIN11","preco":8.15,"nome":"NIKOS INFRA CI","data_atualizacao":"26/01/2026 20:26"},{"ticker":"OGHY11","preco":8.72,"nome":"FII ORAMA   CI","data_atualizacao":"26/01/2026 20:26"},{"ticker":"OCRE11","preco":89,"nome":"FII OCTO    CI","data_atualizacao":"26/01/2026 20:26"},{"ticker":"OBAL11","preco":1095,"nome":"FII OPPBAL  CI","data_atualizacao":"26/01/2026 20:26"},{"ticker":"NVHO11","preco":12,"nome":"FII NOVOHORICI","data_atualizacao":"26/01/2026 20:26"},{"ticker":"NUIF11","preco":93.99,"nome":"NU INFRA FICCI","data_atualizacao":"26/01/2026 20:26"},{"ticker":"NSLU11","preco":209.2,"nome":"FII LOURDES CI","data_atualizacao":"26/01/2026 20:26"},{"ticker":"NEXG11","preco":129,"nome":"FIAGRO NEXG CI","data_atualizacao":"26/01/2026 20:26"},{"ticker":"NEWU11","preco":110.59,"nome":"FII NEWRU   CI","data_atualizacao":"26/01/2026 20:26"},{"ticker":"NEWL11","preco":114.5,"nome":"FII NEWPORT CI","data_atualizacao":"26/01/2026 20:26"},{"ticker":"NCRI11","preco":8.75,"nome":"FII NAVI CRICI","data_atualizacao":"26/01/2026 20:26"},{"ticker":"NAVT11","preco":76.07,"nome":"FII NAVI TOTCI  ER","data_atualizacao":"26/01/2026 20:26"},{"ticker":"KOPA11","preco":603.01,"nome":"FIAGRO KOPA CI  ERA","data_atualizacao":"26/01/2026 20:26"},{"ticker":"KNUQ11","preco":105.15,"nome":"FII KINEA UNCI","data_atualizacao":"26/01/2026 20:26"},{"ticker":"KNRI11","preco":163.21,"nome":"FII KINEA   CI","data_atualizacao":"26/01/2026 20:26"},{"ticker":"KNRE11","preco":0.32,"nome":"FII KII REALCI","data_atualizacao":"26/01/2026 20:26"},{"ticker":"KNHY11","preco":99.53,"nome":"FII KINEA HYCI","data_atualizacao":"26/01/2026 20:26"},{"ticker":"KNHF11","preco":97.6,"nome":"FII KINEA HFCI","data_atualizacao":"26/01/2026 20:26"},{"ticker":"KNCA11","preco":98.1,"nome":"FIAGRO KINEACI","data_atualizacao":"26/01/2026 20:26"},{"ticker":"KIVO11","preco":66.7,"nome":"FII KIVO    CI","data_atualizacao":"26/01/2026 20:26"},{"ticker":"KISU11","preco":7.01,"nome":"FII KILIMA  CI","data_atualizacao":"26/01/2026 20:26"},{"ticker":"KFOF11","preco":85.89,"nome":"FII KINEAFOFCI","data_atualizacao":"26/01/2026 20:26"},{"ticker":"KFEN11","preco":1100,"nome":"FII KFEN    CI","data_atualizacao":"26/01/2026 20:26"},{"ticker":"KEVE11","preco":637,"nome":"FII EVEN II CI","data_atualizacao":"26/01/2026 20:26"},{"ticker":"KDOL11","preco":91.2,"nome":"FIAGRO KDOL CI","data_atualizacao":"26/01/2026 20:26"},{"ticker":"KDIF11","preco":130.61,"nome":"KINEA INFRAFCI","data_atualizacao":"26/01/2026 20:26"},{"ticker":"KCRE11","preco":8.89,"nome":"FII KINEA CRCI","data_atualizacao":"26/01/2026 20:26"},{"ticker":"JURO11","preco":104,"nome":"SPARTA INFRACI","data_atualizacao":"26/01/2026 20:26"},{"ticker":"JSCR11","preco":8.37,"nome":"FII JSCR    CI","data_atualizacao":"26/01/2026 20:26"},{"ticker":"JSAF11","preco":8.09,"nome":"FII JS A FINCI","data_atualizacao":"26/01/2026 20:26"},{"ticker":"JPPA11","preco":86.99,"nome":"FII JPPA CRICI","data_atualizacao":"26/01/2026 20:26"},{"ticker":"JMBI11","preco":92.27,"nome":"INFRA JMBI  CI","data_atualizacao":"26/01/2026 20:26"},{"ticker":"JGPX11","preco":71.75,"nome":"FIAGRO JGP  CI","data_atualizacao":"26/01/2026 20:26"},{"ticker":"JFLL11","preco":65,"nome":"FII JFL LIV CI","data_atualizacao":"26/01/2026 20:26"},{"ticker":"JCIN11","preco":148.9,"nome":"FII JCIN    CI  ER","data_atualizacao":"26/01/2026 20:26"},{"ticker":"JCCJ11","preco":158,"nome":"FII JHSF CJ CI  ER","data_atualizacao":"26/01/2026 20:26"},{"ticker":"JBFO11","preco":82.01,"nome":"JBFO11.SA,0P0001OH6Y,0","data_atualizacao":"26/01/2026 20:26"},{"ticker":"JASC11","preco":99.28,"nome":"FII JASC RENCI  ER","data_atualizacao":"26/01/2026 20:26"},{"ticker":"ITRI11","preco":85.77,"nome":"FII ITRI    CI","data_atualizacao":"26/01/2026 20:26"},{"ticker":"ITIT11","preco":72.31,"nome":"FII INTER ITCI","data_atualizacao":"26/01/2026 20:26"},{"ticker":"ITIP11","preco":66,"nome":"FII INTER IPCI","data_atualizacao":"26/01/2026 20:26"},{"ticker":"ISCJ11","preco":50.71,"nome":"FII ISCJ    CI  ER","data_atualizacao":"26/01/2026 20:26"},{"ticker":"IRIM11","preco":68.76,"nome":"FII IRIM    CI","data_atualizacao":"26/01/2026 20:26"},{"ticker":"IRIF11","preco":9.4,"nome":"INFRA IRIF  CI","data_atualizacao":"26/01/2026 20:26"},{"ticker":"INRD11","preco":76.14,"nome":"FII INTER RDCI","data_atualizacao":"26/01/2026 20:26"},{"ticker":"INLG11","preco":77.03,"nome":"FII INTER LGCI","data_atualizacao":"26/01/2026 20:26"},{"ticker":"INFB11","preco":93.5,"nome":"INFB INFRA  CI","data_atualizacao":"26/01/2026 20:26"},{"ticker":"INDE11","preco":76,"nome":"FII INDE    CI","data_atualizacao":"26/01/2026 20:26"},{"ticker":"IFRI11","preco":104.92,"nome":"FI ITAU IFRICI","data_atualizacao":"26/01/2026 20:26"},{"ticker":"IFRA11","preco":100.64,"nome":"FI ITAUINFRACI","data_atualizacao":"26/01/2026 20:26"},{"ticker":"DVLP11","preco":149.69,"nome":"FII DVLP    CI","data_atualizacao":"26/01/2026 20:26"},{"ticker":"DVFF11","preco":5.93,"nome":"FII DEVA FOFCI","data_atualizacao":"26/01/2026 20:26"},{"ticker":"DPRO11","preco":6.83,"nome":"FII DEVA PROCI","data_atualizacao":"26/01/2026 20:26"},{"ticker":"DOMC11","preco":439,"nome":"DOMC11.SA,0P00013U1X,0","data_atualizacao":"26/01/2026 20:26"},{"ticker":"DMAC11","preco":13,"nome":"DMAC11.SA,0P0001IG9I,0","data_atualizacao":"26/01/2026 20:26"},{"ticker":"DCRA11","preco":7.75,"nome":"FIAGRO DEVANCI","data_atualizacao":"26/01/2026 20:26"},{"ticker":"DAMA11","preco":7.75,"nome":"FII DAMA    CI","data_atualizacao":"26/01/2026 20:26"},{"ticker":"CYLD11","preco":149.73,"nome":"FII CYLD    CI","data_atualizacao":"26/01/2026 20:26"},{"ticker":"CYCR11","preco":8.94,"nome":"FII CYRELA  CI","data_atualizacao":"26/01/2026 20:26"},{"ticker":"CXTL11","preco":328.83,"nome":"FII CX TRX  CI","data_atualizacao":"26/01/2026 20:26"},{"ticker":"CXRI11","preco":66.61,"nome":"FII CX RBRAVCI","data_atualizacao":"26/01/2026 20:26"},{"ticker":"CXCO11","preco":70.33,"nome":"FII CEF CORPCI","data_atualizacao":"26/01/2026 20:26"},{"ticker":"CXCI11","preco":71.92,"nome":"FII CAIXA CICI","data_atualizacao":"26/01/2026 20:26"},{"ticker":"CXAG11","preco":77.2,"nome":"FII CAIXA AGCI","data_atualizacao":"26/01/2026 20:26"},{"ticker":"CTXT11","preco":5.37,"nome":"FII C TEXTILCI","data_atualizacao":"26/01/2026 20:26"},{"ticker":"CTEM11","preco":6,"nome":"FIAGRO CTEM CI","data_atualizacao":"26/01/2026 20:26"},{"ticker":"CRFF11","preco":76.69,"nome":"FII CX RBRA2CI","data_atualizacao":"26/01/2026 20:26"},{"ticker":"CRAA11","preco":97.09,"nome":"FIAGRO CRAA CI","data_atualizacao":"26/01/2026 20:26"},{"ticker":"CPUR11","preco":10.94,"nome":"FII CPHBC URCI  ER","data_atualizacao":"26/01/2026 20:26"},{"ticker":"CPTR11","preco":8.44,"nome":"FIAGRO CPTR CI  ER","data_atualizacao":"26/01/2026 20:26"},{"ticker":"CPTI11","preco":89.99,"nome":"FIC IE CAP  CI","data_atualizacao":"26/01/2026 20:26"},{"ticker":"CPSH11","preco":11.02,"nome":"FII CPSH    CI  ER","data_atualizacao":"26/01/2026 20:26"},{"ticker":"CPOF11","preco":110,"nome":"FII CPOF    CI  ER","data_atualizacao":"26/01/2026 20:26"},{"ticker":"CPLG11","preco":13.04,"nome":"FII CPLG    CI","data_atualizacao":"26/01/2026 20:26"},{"ticker":"CPFF11","preco":69.9,"nome":"FII CAP REITCI","data_atualizacao":"26/01/2026 20:26"},{"ticker":"CNES11","preco":1.83,"nome":"FII CENESP  CI  ER","data_atualizacao":"26/01/2026 20:26"},{"ticker":"CLIN11","preco":91.21,"nome":"FII CLAVE INCI","data_atualizacao":"26/01/2026 20:26"},{"ticker":"CJCT11","preco":64.5,"nome":"FII CJCTOWERCI","data_atualizacao":"26/01/2026 20:26"},{"ticker":"CFII11","preco":768.97,"nome":"FII CF3 IMOBCI","data_atualizacao":"26/01/2026 20:26"},{"ticker":"CFHI11","preco":0,"nome":"FII CF2     CI","data_atualizacao":"26/01/2026 20:26"},{"ticker":"CEOC11","preco":46.11,"nome":"FII CEO CCP CI","data_atualizacao":"26/01/2026 20:26"},{"ticker":"CENU11","preco":100,"nome":"CENU11.SA,0P0001SAKM,0","data_atualizacao":"26/01/2026 20:26"},{"ticker":"CDII11","preco":109.2,"nome":"SPARTA CDII CI","data_atualizacao":"26/01/2026 20:26"},{"ticker":"CCVA11","preco":100.07,"nome":"FII CCVA    CI  ER","data_atualizacao":"26/01/2026 20:26"},{"ticker":"CCRF11","preco":92.5,"nome":"RBR CRI FII CI","data_atualizacao":"26/01/2026 20:26"},{"ticker":"CCME11","preco":9.17,"nome":"FII CANUMA  CI","data_atualizacao":"26/01/2026 20:26"},{"ticker":"CBOP11","preco":40.03,"nome":"FII CBOP PAXCI","data_atualizacao":"26/01/2026 20:26"},{"ticker":"CARE11","preco":1.12,"nome":"FII DEA CARECI","data_atualizacao":"26/01/2026 20:26"},{"ticker":"CACR11","preco":86.02,"nome":"CARTESIA FIICI","data_atualizacao":"26/01/2026 20:26"},{"ticker":"BZLI11","preco":19.78,"nome":"FII BRREALTYCI","data_atualizacao":"26/01/2026 20:26"},{"ticker":"BVAR11","preco":1260.89,"nome":"FII B VAREJOCI  ERA","data_atualizacao":"26/01/2026 20:26"},{"ticker":"BTYU11","preco":9.6,"nome":"FII BTYU    CI  ER","data_atualizacao":"26/01/2026 20:26"},{"ticker":"BTWR11","preco":105.49,"nome":"FII BTOWERS CI","data_atualizacao":"26/01/2026 20:26"},{"ticker":"BTSI11","preco":109.59,"nome":"FII BTSP II CI  ER","data_atualizacao":"26/01/2026 20:26"},{"ticker":"BTSG11","preco":146.92,"nome":"FII BTSP I  CI","data_atualizacao":"26/01/2026 20:26"},{"ticker":"BTRA11","preco":70.01,"nome":"FII BTG TAGRCI  ER","data_atualizacao":"26/01/2026 20:26"},{"ticker":"BTML11","preco":111.28,"nome":"BTML11.SA,0P0001PUB1,0","data_atualizacao":"26/01/2026 20:26"},{"ticker":"BTHI11","preco":43.5,"nome":"BTG HOTEL FICI","data_atualizacao":"26/01/2026 20:26"},{"ticker":"BTHF11","preco":9.56,"nome":"FII BTHF    CI","data_atualizacao":"26/01/2026 20:26"},{"ticker":"BTCI11","preco":9.34,"nome":"FII BTG CRI CI","data_atualizacao":"26/01/2026 20:26"},{"ticker":"BTAL11","preco":84.8,"nome":"FII BTG AGROCI  ER","data_atualizacao":"26/01/2026 20:26"},{"ticker":"BTAG11","preco":108.5,"nome":"FIAGRO BTAG CI","data_atualizacao":"26/01/2026 20:26"},{"ticker":"BROF11","preco":58.31,"nome":"FII BROF    CI  ER","data_atualizacao":"26/01/2026 20:26"},{"ticker":"BRIP11","preco":417.97,"nome":"FII BRIO IIICI","data_atualizacao":"26/01/2026 20:26"},{"ticker":"BRIM11","preco":282.15,"nome":"FII BRIO II CI","data_atualizacao":"26/01/2026 20:26"},{"ticker":"BRFT11","preco":85.98,"nome":"FIAGRO BRFT CI","data_atualizacao":"26/01/2026 20:26"},{"ticker":"AROA11","preco":1.07,"nome":"FII AROA    CI","data_atualizacao":"26/01/2026 20:26"},{"ticker":"ARFI11B","preco":1109,"nome":"ARFI11B.SA,0P0001BRBJ,0","data_atualizacao":"26/01/2026 20:26"},{"ticker":"AQLL11","preco":385.03,"nome":"AQLL11.SA,0P00013U1K,0","data_atualizacao":"26/01/2026 20:26"},{"ticker":"APXU11","preco":95,"nome":"FII APXU    CI","data_atualizacao":"26/01/2026 20:26"},{"ticker":"APXR11","preco":100,"nome":"FII APXR    CI","data_atualizacao":"26/01/2026 20:26"},{"ticker":"APXM11","preco":82.75,"nome":"FII APEX MS CI  ER","data_atualizacao":"26/01/2026 20:26"},{"ticker":"APTO11","preco":8.79,"nome":"FII NAVI RSDCI","data_atualizacao":"26/01/2026 20:26"},{"ticker":"ALZM11","preco":6.4,"nome":"FII ALIANZMECI  ER","data_atualizacao":"26/01/2026 20:26"},{"ticker":"ALZC11","preco":7.87,"nome":"FII ALIANZACCI  ER","data_atualizacao":"26/01/2026 20:26"},{"ticker":"ALMI11","preco":631.29,"nome":"FII TORRE ALCI","data_atualizacao":"26/01/2026 20:26"},{"ticker":"AJFI11","preco":8.2,"nome":"FII AJ MALLSCI  ES","data_atualizacao":"26/01/2026 20:26"},{"ticker":"AIEC11","preco":52.92,"nome":"FII AUTONOMYCI","data_atualizacao":"26/01/2026 20:26"},{"ticker":"AGRX11","preco":8.73,"nome":"FIAGRO AGRX CI","data_atualizacao":"26/01/2026 20:26"},{"ticker":"AFOF11","preco":91.6,"nome":"AFOF11.SA,0P0001OFVH,0","data_atualizacao":"26/01/2026 20:26"},{"ticker":"AFHI11","preco":95.33,"nome":"FII AFHI CRICI  ER","data_atualizacao":"26/01/2026 20:26"},{"ticker":"AFCR11","preco":103.15,"nome":"AFCR11.SA,0P0001K58C,0","data_atualizacao":"26/01/2026 20:26"},{"ticker":"ABCP11","preco":82,"nome":"FII ABC IMOBCI","data_atualizacao":"26/01/2026 20:26"},{"ticker":"AAZQ11","preco":8.58,"nome":"FIAGRO AAZQ CI","data_atualizacao":"26/01/2026 20:26"},{"ticker":"AAGR11","preco":96.71,"nome":"FIAGRO AAGR CI","data_atualizacao":"26/01/2026 20:26"},{"ticker":"GGRC11","preco":10.04,"nome":"FII GGRCOVEPCI","data_atualizacao":"26/01/2026 20:26"},{"ticker":"IBBP11","preco":8.8,"nome":"FII IBBP    CI","data_atualizacao":"26/01/2026 20:26"},{"ticker":"SNEL11","preco":8.61,"nome":"FII SUNO EL CI  ER","data_atualizacao":"26/01/2026 20:26"},{"ticker":"SNAG11","preco":11.14,"nome":"FIAGRO SUNO CI  ER","data_atualizacao":"26/01/2026 20:26"},{"ticker":"RBRP11","preco":55.23,"nome":"FII RBR PROPCI","data_atualizacao":"26/01/2026 20:26"},{"ticker":"JSRE11","preco":67.5,"nome":"FII JS REAL CI","data_atualizacao":"26/01/2026 20:26"},{"ticker":"DEVA11","preco":27.23,"nome":"FII DEVANT  CI","data_atualizacao":"26/01/2026 20:26"},{"ticker":"HCTR11","preco":23.07,"nome":"FII HECTARE CI","data_atualizacao":"26/01/2026 20:26"},{"ticker":"RECT11","preco":39.1,"nome":"FII REC RENDCI","data_atualizacao":"26/01/2026 20:26"},{"ticker":"RBRR11","preco":89.41,"nome":"FII RBRHGRADCI","data_atualizacao":"26/01/2026 20:26"},{"ticker":"ALZR11","preco":10.72,"nome":"FII ALIANZA CI  ERS","data_atualizacao":"26/01/2026 20:26"},{"ticker":"KNSC11","preco":9.07,"nome":"FII KINEA SCCI","data_atualizacao":"26/01/2026 20:26"},{"ticker":"TGAR11","preco":93.2,"nome":"FII TG ATIVOCI","data_atualizacao":"26/01/2026 20:26"},{"ticker":"VGHF11","preco":7.18,"nome":"FII VALOR HECI","data_atualizacao":"26/01/2026 20:26"},{"ticker":"PVBI11","preco":82.39,"nome":"FII PVBI VBICI","data_atualizacao":"26/01/2026 20:26"},{"ticker":"BRCO11","preco":119.33,"nome":"FII BRESCO  CI","data_atualizacao":"26/01/2026 20:26"},{"ticker":"HGRU11","preco":129.3,"nome":"FII HGRU PAXCI","data_atualizacao":"26/01/2026 20:26"},{"ticker":"IRDM11","preco":58.5,"nome":"FII IRIDIUM CI  ER","data_atualizacao":"26/01/2026 20:26"},{"ticker":"BTLG11","preco":102.75,"nome":"FII BTLG    CI  ER","data_atualizacao":"26/01/2026 20:26"},{"ticker":"CPTS11","preco":8.03,"nome":"FII CAPI SECCI  ERS","data_atualizacao":"26/01/2026 20:26"},{"ticker":"KNCR11","preco":106.4,"nome":"FII KINEA RICI","data_atualizacao":"26/01/2026 20:26"},{"ticker":"XPML11","preco":109.5,"nome":"FII XP MALLSCI  ER","data_atualizacao":"26/01/2026 20:26"},{"ticker":"XPLG11","preco":102.7,"nome":"FII XP LOG  CI","data_atualizacao":"26/01/2026 20:26"},{"ticker":"VISC11","preco":109.35,"nome":"FII VINCI SCCI","data_atualizacao":"26/01/2026 20:26"},{"ticker":"KNIP11","preco":91.8,"nome":"FII KINEA IPCI","data_atualizacao":"26/01/2026 20:26"},{"ticker":"HGLG11","preco":157.37,"nome":"FII HGLG PAXCI","data_atualizacao":"26/01/2026 20:26"},{"ticker":"MXRF11","preco":9.5,"nome":"FII MAXI RENCI","data_atualizacao":"26/01/2026 20:26"},{"ticker":"UBSR11","preco":102.5,"nome":"UBSR11.SA,0P0001BRC4,0","data_atualizacao":"26/01/2026 20:26"},{"ticker":"TVRI11","preco":102.99,"nome":"FII TIVIO RICI","data_atualizacao":"26/01/2026 20:26"},{"ticker":"TSNC11","preco":81.06,"nome":"FII TRANSINCCI","data_atualizacao":"26/01/2026 20:26"},{"ticker":"TSER11","preco":97,"nome":"FII TISHMAN CI","data_atualizacao":"26/01/2026 20:26"},{"ticker":"TRXY11","preco":9.4,"nome":"FII TRXY    CI  ES","data_atualizacao":"26/01/2026 20:26"},{"ticker":"TRXF11","preco":95.51,"nome":"FII TRX REALCI","data_atualizacao":"26/01/2026 20:26"},{"ticker":"TRXB11","preco":179.97,"nome":"FII TRX R IICI","data_atualizacao":"26/01/2026 20:26"},{"ticker":"TRNT11","preco":95.58,"nome":"FII TORRE NOCI","data_atualizacao":"26/01/2026 20:26"},{"ticker":"TRBL11","preco":66.51,"nome":"FII SDI LOG CI","data_atualizacao":"26/01/2026 20:26"},{"ticker":"TORD11","preco":1.86,"nome":"FII TORDE EICI","data_atualizacao":"26/01/2026 20:26"},{"ticker":"TOPP11","preco":74.32,"nome":"FII TOPP    CI  ER","data_atualizacao":"26/01/2026 20:26"},{"ticker":"TMPS11","preco":86,"nome":"FII ITAU TEMCI","data_atualizacao":"26/01/2026 20:26"},{"ticker":"TJKB11","preco":254.66,"nome":"FII TJK RENDCI  ER","data_atualizacao":"26/01/2026 20:26"},{"ticker":"THRA11","preco":138.5,"nome":"THRA11.SA,0P00013U29,0","data_atualizacao":"26/01/2026 20:26"},{"ticker":"TEPP11","preco":8.69,"nome":"FII TEL PROPCI","data_atualizacao":"26/01/2026 20:26"},{"ticker":"TELM11","preco":10,"nome":"FII TELM    CI  ER","data_atualizacao":"26/01/2026 20:26"},{"ticker":"TCIN11","preco":145.92,"nome":"FII TOUR V  CI","data_atualizacao":"26/01/2026 20:26"},{"ticker":"TBOF11","preco":101.5,"nome":"TBOF11.SA,0P00013U2Q,0","data_atualizacao":"26/01/2026 20:26"},{"ticker":"STRX11","preco":141.96,"nome":"FII STARX   CI","data_atualizacao":"26/01/2026 20:26"},{"ticker":"SRVD11","preco":3,"nome":"SRVD11.SA,0P0001OH79,0","data_atualizacao":"26/01/2026 20:26"},{"ticker":"SPXS11","preco":8.97,"nome":"FII SPX SYN CI","data_atualizacao":"26/01/2026 20:26"},{"ticker":"SPTW11","preco":41,"nome":"FII SPTW PAXCI","data_atualizacao":"26/01/2026 20:26"},{"ticker":"SPMO11","preco":122,"nome":"FII SUPREMO CI","data_atualizacao":"26/01/2026 20:26"},{"ticker":"SPGM11","preco":12.89,"nome":"FII SPGM    CI","data_atualizacao":"26/01/2026 20:26"},{"ticker":"SPDE11","preco":1266.67,"nome":"FII WHG F SPCI  ER","data_atualizacao":"26/01/2026 20:26"},{"ticker":"SOLR11","preco":1051.35,"nome":"SOLR11.SA,0P0001OH77,0","data_atualizacao":"26/01/2026 20:26"},{"ticker":"SNME11","preco":9.78,"nome":"FII SNME    CI  ER","data_atualizacao":"26/01/2026 20:26"},{"ticker":"SNLG11","preco":1.27,"nome":"FII SUNO LG CI","data_atualizacao":"26/01/2026 20:26"},{"ticker":"SNID11","preco":11.3,"nome":"SUNO FIC FI CI  ER","data_atualizacao":"26/01/2026 20:26"},{"ticker":"SNFZ11","preco":9.77,"nome":"FIAGRO SNFZ CI  ER","data_atualizacao":"26/01/2026 20:26"},{"ticker":"SNFF11","preco":77.8,"nome":"FII SUNOFOFICI  ER","data_atualizacao":"26/01/2026 20:26"},{"ticker":"SNCI11","preco":85.82,"nome":"FII SUNO CRICI  ER","data_atualizacao":"26/01/2026 20:26"},{"ticker":"SMRE11","preco":65,"nome":"FII SMRE    CI","data_atualizacao":"26/01/2026 20:26"},{"ticker":"SJAU11","preco":0.9,"nome":"FII SJ AU   CI","data_atualizacao":"26/01/2026 20:26"},{"ticker":"SHPP11","preco":10,"nome":"FII SHPP    CI  ER","data_atualizacao":"26/01/2026 20:26"},{"ticker":"IDGR11","preco":1.5,"nome":"FII UNID II CI","data_atualizacao":"26/01/2026 20:26"},{"ticker":"IDFI11","preco":2,"nome":"FII UNIDADESCI","data_atualizacao":"26/01/2026 20:26"},{"ticker":"ICRI11","preco":91.97,"nome":"FII CI IPCA CI","data_atualizacao":"26/01/2026 20:26"},{"ticker":"ICNE11","preco":769.63,"nome":"FII ICNE    CI","data_atualizacao":"26/01/2026 20:26"},{"ticker":"IBFF11","preco":66.4,"nome":"IBFF11.SA,0P0001K5M9,0","data_atualizacao":"26/01/2026 20:26"},{"ticker":"IBCR11","preco":49,"nome":"FII BREI    CI","data_atualizacao":"26/01/2026 20:26"},{"ticker":"IAGR11","preco":4.4,"nome":"FIAGRO SFI  CI","data_atualizacao":"26/01/2026 20:26"},{"ticker":"IAAG11","preco":8.91,"nome":"FIAGRO IAAG CI","data_atualizacao":"26/01/2026 20:26"},{"ticker":"HUSI11","preco":1220,"nome":"FII HUSI    CI","data_atualizacao":"26/01/2026 20:26"},{"ticker":"HUSC11","preco":96.01,"nome":"FII H UNIMEDCI","data_atualizacao":"26/01/2026 20:26"},{"ticker":"HUCG11","preco":94.99,"nome":"FII UNIMED CCI","data_atualizacao":"26/01/2026 20:26"},{"ticker":"HTMX11","preco":143.31,"nome":"FII HOTEL MXCI","data_atualizacao":"26/01/2026 20:26"},{"ticker":"HSRE11","preco":108,"nome":"FII HSIRENDACI","data_atualizacao":"26/01/2026 20:26"},{"ticker":"HSML11","preco":91.38,"nome":"FII HSI MALLCI","data_atualizacao":"26/01/2026 20:26"},{"ticker":"HSLG11","preco":91.48,"nome":"FII HSI LOG CI","data_atualizacao":"26/01/2026 20:26"},{"ticker":"HSAF11","preco":79.3,"nome":"FII HSI CRI CI","data_atualizacao":"26/01/2026 20:26"},{"ticker":"HRES11","preco":145.45,"nome":"FII HIRE RESCI","data_atualizacao":"26/01/2026 20:26"},{"ticker":"HREC11","preco":8.25,"nome":"FII HEDGERECCI","data_atualizacao":"26/01/2026 20:26"},{"ticker":"HRDF11","preco":4,"nome":"FII HREALTY CI","data_atualizacao":"26/01/2026 20:26"},{"ticker":"HPDP11","preco":87.67,"nome":"FII HEDGEPDPCI","data_atualizacao":"26/01/2026 20:26"},{"ticker":"HOSI11","preco":85.55,"nome":"FII HOUSI   CI","data_atualizacao":"26/01/2026 20:26"},{"ticker":"HOMS11","preco":122.11,"nome":"FII HOMS    CI","data_atualizacao":"26/01/2026 20:26"},{"ticker":"HOFC11","preco":29.77,"nome":"FII HOFFICEICI","data_atualizacao":"26/01/2026 20:26"},{"ticker":"HMOC11","preco":226.95,"nome":"HMOC11.SA,0P0001IGJ0,0","data_atualizacao":"26/01/2026 20:26"},{"ticker":"HLOG11","preco":9.25,"nome":"FII HEDGELOGCI","data_atualizacao":"26/01/2026 20:26"},{"ticker":"HILG11","preco":186.81,"nome":"FII HIRE LOGCI","data_atualizacao":"26/01/2026 20:26"},{"ticker":"HGRE11","preco":126.92,"nome":"FII HGRE PAXCI","data_atualizacao":"26/01/2026 20:26"},{"ticker":"HGPO11","preco":145.73,"nome":"FII HGPO PAXCI","data_atualizacao":"26/01/2026 20:26"},{"ticker":"HGIC11","preco":67.92,"nome":"FII HGI CRI CI","data_atualizacao":"26/01/2026 20:26"},{"ticker":"HGFF11","preco":0,"nome":"FII HGFF PAXCI","data_atualizacao":"26/01/2026 20:26"},{"ticker":"HGCR11","preco":98.62,"nome":"FII HGCR PAXCI","data_atualizacao":"26/01/2026 20:26"},{"ticker":"HGBS11","preco":19.97,"nome":"FII HEDGEBS CI","data_atualizacao":"26/01/2026 20:26"},{"ticker":"HGBL11","preco":9.24,"nome":"FII HGBL    CI","data_atualizacao":"26/01/2026 20:26"},{"ticker":"HGAG11","preco":16.99,"nome":"FIAGRO HIGH CI","data_atualizacao":"26/01/2026 20:26"},{"ticker":"HFOF11","preco":6.86,"nome":"FII HTOPFOF3CI","data_atualizacao":"26/01/2026 20:26"},{"ticker":"HDOF11","preco":94,"nome":"FII HEDGE OFCI","data_atualizacao":"26/01/2026 20:26"},{"ticker":"HDEL11","preco":101.51,"nome":"FII HEDGE DVCI","data_atualizacao":"26/01/2026 20:26"},{"ticker":"HCST11","preco":45,"nome":"FII HECT DESCI  ES","data_atualizacao":"26/01/2026 20:26"},{"ticker":"HCRI11","preco":315.39,"nome":"FII CRIANCA CI  ER","data_atualizacao":"26/01/2026 20:26"},{"ticker":"HCRA11","preco":10.22,"nome":"FIAGRO HEDGECI","data_atualizacao":"26/01/2026 20:26"},{"ticker":"HCHG11","preco":85.17,"nome":"FII HECT CRICI","data_atualizacao":"26/01/2026 20:26"},{"ticker":"HBCR11","preco":136.01,"nome":"FII HBC REN CI","data_atualizacao":"26/01/2026 20:26"},{"ticker":"FISC11","preco":60,"nome":"FII SC 401  CI","data_atualizacao":"26/01/2026 20:26"},{"ticker":"FIIB11","preco":477.9,"nome":"FII INDL BR CI","data_atualizacao":"26/01/2026 20:26"},{"ticker":"FIGS11","preco":47.18,"nome":"FII GEN SHOPCI","data_atualizacao":"26/01/2026 20:26"},{"ticker":"FGAA11","preco":9.23,"nome":"FIAGRO FGA  CI","data_atualizacao":"26/01/2026 20:26"},{"ticker":"FCFL11","preco":125.82,"nome":"FII CAMPUSFLCI  ER","data_atualizacao":"26/01/2026 20:26"},{"ticker":"FATN11","preco":88.38,"nome":"FII ATHENA ICI","data_atualizacao":"26/01/2026 20:26"},{"ticker":"BBIG11","preco":7.4,"nome":"FII BBIG    CI","data_atualizacao":"26/01/2026 20:26"},{"ticker":"BBGO11","preco":77.87,"nome":"FIAGRO BBGO CI","data_atualizacao":"26/01/2026 20:26"},{"ticker":"BBFO11","preco":66.3,"nome":"FII BB FOF  CI","data_atualizacao":"26/01/2026 20:26"},{"ticker":"BARI11","preco":79.2,"nome":"FII BARI VBICI","data_atualizacao":"26/01/2026 20:26"},{"ticker":"AZPL11","preco":7.7,"nome":"FII AZPL    CI","data_atualizacao":"26/01/2026 20:26"},{"ticker":"AURB11","preco":81,"nome":"FII ALI URB CI  ER","data_atualizacao":"26/01/2026 20:26"},{"ticker":"ATSA11B","preco":1049.99,"nome":"ATSA11B.SA,0P00013U1S,0","data_atualizacao":"26/01/2026 20:26"},{"ticker":"ATSA11","preco":57.51,"nome":"FII HATRIUM CI","data_atualizacao":"26/01/2026 20:26"},{"ticker":"ASRF11","preco":10974,"nome":"FII ASA RET CI","data_atualizacao":"26/01/2026 20:26"},{"ticker":"ARXD11","preco":7.74,"nome":"FII ARXD R  CI","data_atualizacao":"26/01/2026 20:26"},{"ticker":"ARRI11","preco":6.62,"nome":"FII ATRIO   CI","data_atualizacao":"26/01/2026 20:26"}]